{
  "settings": [
  ],
  "dependencies": {
    "R": [
      {
        "name": "move2"
      },
	        {
        "name": "dplyr"
      },
	        {
        "name": "magrittr"
      },
	        {
        "name": "lubridate"
      },
	        {
        "name": "circular"
      },
	        {
        "name": "ggplot2"
      },
	        {
        "name": "units"
      },
	        {
        "name": "grid"
      },
	        {
        "name": "gridExtra"
      },
    ]
  },
  "createsArtifacts": true,
  "license": {
    "key": "MIT"
  },
  "language": "eng",
  "keywords": [
    "speed",
    "direction",
	"move2",
	"circular",
	"distribution",
	"month"
  ],
  "people": [
        {
     "firstName": "Andrea",
      "middleInitials": null,
      "lastName": "Kölzsch",
      "email": "akoelzsch@ab.mpg.de",
      "roles": [
        "author",
        "creator"
      ],
      "orcid": "0000-0003-0193-1563",
      "affiliation": "Max-Planck-Institute of Animal Behavior",
      "affiliationRor": "https://ror.org/026stee22"
    },
	{
      "firstName": "Bart",
      "middleInitials": null,
      "lastName": "Kranstauber",
      "email": "b.kranstauber@uva.nl",
      "roles": ["author"]
    }
  ],
  
  "references": [
    {
      "type": "IsVariantFormOf",
      "note": "Trajectory analysis of turkey vultures with move2",
      "url": "https://bartk.gitlab.io/move2/articles/trajectory_analysis.html"
    }
  ],
  "documentation": {
    "url": "https://github.com/movestore/Speed-Direction-Plots/blob/master/README.md"
  }
}

